pyhli.cp36-win_amd64.pyd
pyhli-0.0.12.data/scripts/pyhli_hello_world.py
pyhli-0.0.12.data/scripts/pyhli_retrieve_series.py
pyhli-0.0.12.data/scripts/pyhli_versions.py
pyhli-0.0.12.dist-info/LICENSE.txt
pyhli-0.0.12.dist-info/METADATA
pyhli-0.0.12.dist-info/RECORD
pyhli-0.0.12.dist-info/WHEEL
pyhli-0.0.12.dist-info/top_level.txt
