Metadata-Version: 2.1
Name: pyhli
Version: 0.0.12
Summary: Python Host Language Interface for FAME
Home-page: http://github.com/qomaio/pyhli
Author: Qoma LLC
Author-email: info@qoma.io
License: AGPLv3
Platform: any
